{
    "states": {
        "AK": "w",
        "AL": "s",
        "AR": "s",
        "AZ": "w",
        "CA": "w",
        "CO": "w",
        "CT": "ne",
        "DC": "s",
        "DE": "s",
        "FL": "s",
        "GA": "s",
        "HI": "w",
        "IA": "mw",
        "ID": "w",
        "IL": "mw",
        "IN": "mw",
        "KS": "mw",
        "KY": "s",
        "LA": "s",
        "MA": "ne",
        "MD": "s",
        "ME": "ne",
        "MI": "mw",
        "MN": "mw",
        "MO": "mw",
        "MS": "s",
        "MT": "w",
        "NC": "s",
        "ND": "mw",
        "NE": "mw",
        "NH": "ne",
        "NJ": "ne",
        "NM": "w",
        "NV": "w",
        "NY": "ne",
        "OH": "mw",
        "OK": "s",
        "OR": "w",
        "PA": "ne",
        "RI": "ne",
        "SC": "s",
        "SD": "mw",
        "TN": "s",
        "TX": "s",
        "UT": "w",
        "VA": "s",
        "VT": "ne",
        "WA": "w",
        "WI": "mw",
        "WV": "s",
        "WY": "w"
    }
}